digipath_mltk/__init__.py
digipath_mltk/cli.py
digipath_mltk/run_toolkit.py
digipath_mltk/toolkit.py
digipath_mltk-0.0.0.dist-info/LICENSE
digipath_mltk-0.0.0.dist-info/METADATA
digipath_mltk-0.0.0.dist-info/WHEEL
digipath_mltk-0.0.0.dist-info/top_level.txt
digipath_mltk-0.0.0.dist-info/RECORD
