Metadata-Version: 2.1
Name: digipath-mltk
Version: 0.0.0
Summary: UNKNOWN
Home-page: https://ncsa.github.io/DigiPath_MLTK/
Author: DigiPath_MLTK development team
License: UNKNOWN
Project-URL: Source, https://github.com/ncsa/DigiPath_MLTK
Platform: UNKNOWN
Classifier: License :: OSI Approved :: MIT License
Classifier: Programming Language :: Python :: 3.5
Classifier: Programming Language :: Python :: 3.6
Classifier: Programming Language :: Python :: 3.7
Classifier: Programming Language :: Python :: 3.8
Classifier: Operating System :: OS Independent
Requires-Python: >=3.5
